3b. T Flip-Flop/T_Flip_Flop.v
module T_Flip_Flop(Q, T, clk, reset);
output reg Q;
input T, clk, reset;

always @(posedge clk) begin
    if (reset == 1'b1)
        Q <= 1'b0;
    else 
        Q <= T^Q;
end


endmodule

3b. T Flip-Flop/T_Flip_Flop_tb.v
`include "T_Flip_Flop.v"
module T_Flip_Flop_tb;
wire Q;
reg T, clk, reset;

T_Flip_Flop I1(Q, T, clk, reset);
always begin
   #1 clk = ~clk;
end 
initial begin
    clk = 1;
    reset = 1;
#1  reset = 0;
    T = 1;
#0.5  T = 1;
#0.5 T = 0;
#0.5 T = 1;
#2 T = 1;
#4 T = 0;
#1 T = 1;
end
always begin
    #10 $finish;
end


initial begin
    $monitor("%0t,T = %b Q = %b clk = %b reset = %b ",$time, T, Q, clk, reset);
    $dumpfile("dump.vcd");
    $dumpvars;
end

endmodule

3b. T Flip-Flop/dump.vcd
$date
	Fri Jan 03 11:01:17 2020
$end
$version
	Icarus Verilog
$end
$timescale
	1s
$end
$scope module T_Flip_Flop_tb $end
$var wire 1 ! Q $end
$var reg 1 " T $end
$var reg 1 # clk $end
$var reg 1 $ reset $end
$scope module I1 $end
$var wire 1 " T $end
$var wire 1 # clk $end
$var wire 1 $ reset $end
$var reg 1 ! Q $end
$upscope $end
$upscope $end
$enddefinitions $end
#0
$dumpvars
1$
1#
x"
0!
$end
#1
1"
0$
0#
#2
1!
1#
#3
0"
0#
#4
0!
1"
1#
#5
0#
#6
1!
1#
#7
0#
#8
0!
1#
#9
0#
#10
1#
0"
